sshsync/__init__.py
sshsync/cli.py
sshsync/client.py
sshsync/config.py
sshsync/logging.py
sshsync/schemas.py
sshsync/utils.py
sshsync-0.12.0.dist-info/METADATA
sshsync-0.12.0.dist-info/WHEEL
sshsync-0.12.0.dist-info/entry_points.txt
sshsync-0.12.0.dist-info/licenses/LICENSE
sshsync-0.12.0.dist-info/RECORD
