Metadata-Version: 2.4
Name: sshsync
Version: 0.12.0
Summary: sshsync is a CLI tool to run shell commands across multiple servers via SSH, either on specific groups or all servers. It also supports pushing and pulling files to and from remote hosts.
Project-URL: Homepage, https://github.com/Blackmamoth/sshsync
Project-URL: Issues, https://github.com/Blackmamoth/sshsync/issues
Author-email: Blackmamoth <blackmamoth83@gmail.com>
License: MIT
License-File: LICENSE
Requires-Python: >=3.10
Requires-Dist: asyncssh>=2.20.0
Requires-Dist: keyring>=25.6.0
Requires-Dist: pyyaml>=6.0.2
Requires-Dist: rich>=14.0.0
Requires-Dist: sshconf>=0.2.7
Requires-Dist: structlog>=25.3.0
Requires-Dist: typer>=0.15.3
